genspc4awsorg/__init__.py
genspc4awsorg/__main__.py
genspc4awsorg-0.5.0.dist-info/LICENSE
genspc4awsorg-0.5.0.dist-info/METADATA
genspc4awsorg-0.5.0.dist-info/WHEEL
genspc4awsorg-0.5.0.dist-info/entry_points.txt
genspc4awsorg-0.5.0.dist-info/top_level.txt
genspc4awsorg-0.5.0.dist-info/RECORD
