Metadata-Version: 2.1
Name: genspc4awsorg
Version: 0.5.0
Summary: Generate steampipe connection file(.spc) for accounts and OUs in specified AWS organization. Before run this script, please make sure correct AWS credential in envs(using aws-vault is recommend), and base credential profile which can AssumeRole to accounts accross organization has been configured.
Home-page: https://github.com/happy240/steampipe-conn-generator-for-aws-organization
Author: Henry Huo
Author-email: happy78@live.com
Project-URL: Bug Tracker, https://github.com/happy240/steampipe-conn-generator-for-aws-organization/issues
Classifier: Programming Language :: Python :: 3
Classifier: License :: OSI Approved :: GNU General Public License v3 or later (GPLv3+)
Classifier: Operating System :: OS Independent
Requires-Python: >=3.6
License-File: LICENSE
Requires-Dist: boto3 (>=1.19.5)
